.editorconfig
.gitignore
.gitlab-ci.yml
.travis.yml
AUTHORS.rst
CONTRIBUTING.rst
HISTORY.rst
LICENSE
MANIFEST.in
Makefile
README.rst
pyvenv.cfg
requirements_dev.txt
setup.cfg
setup.py
tox.ini
travis_pypi_setup.py
docs/Makefile
docs/authors.rst
docs/conf.py
docs/contributing.rst
docs/history.rst
docs/index.rst
docs/installation.rst
docs/make.bat
docs/readme.rst
docs/sample.ipynb
docs/sample_notebook.png
docs/usage.rst
docs/_build/html/_images/sample_notebook.png
docs/_build/html/_static/ajax-loader.gif
docs/_build/html/_static/comment-bright.png
docs/_build/html/_static/comment-close.png
docs/_build/html/_static/comment.png
docs/_build/html/_static/down-pressed.png
docs/_build/html/_static/down.png
docs/_build/html/_static/file.png
docs/_build/html/_static/minus.png
docs/_build/html/_static/plus.png
docs/_build/html/_static/up-pressed.png
docs/_build/html/_static/up.png
src/log_hunter/__init__.py
src/log_hunter/cli.py
src/log_hunter/log_hunter.py
src/log_hunter.egg-info/PKG-INFO
src/log_hunter.egg-info/SOURCES.txt
src/log_hunter.egg-info/dependency_links.txt
src/log_hunter.egg-info/entry_points.txt
src/log_hunter.egg-info/not-zip-safe
src/log_hunter.egg-info/requires.txt
src/log_hunter.egg-info/top_level.txt
tests/__init__.py
tests/test_log_hunter.py