Metadata-Version: 1.1
Name: log-hunter
Version: 0.5.2
Summary: Library and CLI tool to access kibana logglines in bulk.
Home-page: https://github.com/ptillemans/log_hunter
Author: Peter Tillemans
Author-email: pti@melexis.com
License: Apache Software License 2.0
Keywords: log_hunter
Platform: UNKNOWN
Classifier: Development Status :: 2 - Pre-Alpha
Classifier: Intended Audience :: Developers
Classifier: License :: OSI Approved :: Apache Software License
Classifier: Natural Language :: English
Classifier: Programming Language :: Python :: 2
Classifier: Programming Language :: Python :: 2.6
Classifier: Programming Language :: Python :: 2.7
Classifier: Programming Language :: Python :: 3
Classifier: Programming Language :: Python :: 3.3
Classifier: Programming Language :: Python :: 3.4
Classifier: Programming Language :: Python :: 3.5
Classifier: Programming Language :: Python :: 3.6
